eazy_reverse.py
eazy_reverse-0.1.0.dist-info/WHEEL
eazy_reverse-0.1.0.dist-info/METADATA
eazy_reverse-0.1.0.dist-info/RECORD
